{
  "schemaVersion": "ofarm.plannedintervention.v0.1",
  "plannedInterventionId": "planned-intervention:field-17:row-selective-pruning:2026-04-08",
  "plannedAt": "2026-04-07T18:00:00Z",
  "plannedByPartyRef": "party:farmer:ana-kovac",
  "targetScope": {
    "scopeType": "FIELD",
    "scopeRef": "field:17"
  },
  "interventionKind": "PRUNING_CANOPY_OPENING",
  "plannedWindowStart": "2026-04-08T06:00:00Z",
  "plannedWindowEnd": "2026-04-08T12:00:00Z",
  "planState": "ACTIVE",
  "rationaleNarrativeObservationRefs": [
    "narrative-observation:field-17:west-edge-canopy:2026-04-07"
  ],
  "rationaleLocalMemoryRuleRefs": [
    "local-memory-rule:field-17:west-edge-mildew-window:v1"
  ],
  "localArtifactRefs": [
    "local-artifact:field-17:notebook-page:2026-04-07"
  ],
  "expectedOutcomeSummary": "Open west-edge airflow before the next mildew-risk window while preserving row selectivity for the orchard block.",
  "notes": "Plan object only; AGR-P9 links it to a local-knowledge rationale payload, but later execution must still flow through claim, review, and accepted-consequence law.",
  "interventionIntentPayloadRefs": [
    "intervention-intent:field-17:canopy-pruning:planned-operation:2026-04-07"
  ]
}
