{
  "fixtureId": "charter_missing_non_bypass_clauses_fails",
  "actualPass": false,
  "expectedPass": false,
  "conformanceFixturePassed": true,
  "semanticResults": [],
  "schemaResults": [
    {
      "schemaFile": "03_machine_contracts/drafts_non_default/sustainability_charter/OFARM_SustainableFarmingCharter_schema_v0_1.json",
      "actualSchemaValid": false,
      "schemaErrors": [
        "nonBypassClauses: ['NO_TRUTH_BYPASS'] is too short",
        "nonBypassClauses: ['NO_TRUTH_BYPASS'] does not contain items matching the given schema",
        "nonBypassClauses: ['NO_TRUTH_BYPASS'] does not contain items matching the given schema",
        "nonBypassClauses: ['NO_TRUTH_BYPASS'] does not contain items matching the given schema",
        "nonBypassClauses: ['NO_TRUTH_BYPASS'] does not contain items matching the given schema",
        "nonBypassClauses: ['NO_TRUTH_BYPASS'] does not contain items matching the given schema",
        "nonBypassClauses: ['NO_TRUTH_BYPASS'] does not contain items matching the given schema",
        "nonBypassClauses: ['NO_TRUTH_BYPASS'] does not contain items matching the given schema"
      ],
      "actualSemanticValid": true,
      "semanticError": null
    }
  ]
}
